ALU/ALU.v
`define ADD 4'b0000  // 0b0000 represents addition
`define SUB 4'b0001  // 0b0001 represents subtraction
`define ADDS 4'b0010  // 0b0010 represents add with carry flag
`define SUBS 4'b0011  // 0b0011 represents subtraction with negative flag
`define CMP 4'b0100  // 0b0100 represents comparison
`define AND 4'b0111  // 0b0111 represents bitwise AND
`define OR 4'b1000  // 0b1000 represents bitwise OR
`define XOR 4'b1001  // 0b1001 represents bitwise XOR
`define MVN 4'b1010  // 0b1010 represents bitwise NOT


module ALU(
    input [31:0] operand_a, operand_b,
    input [3:0] alu_control,
    output reg [31:0] result,
    output reg zero_flag,
    output reg carry_flag,
    output reg overflow_flag,
    output reg negative_flag
);
reg [32:0] acc;
    always @(*)
        begin
            zero_flag = 0;
            carry_flag = 0;
            overflow_flag = 0;
            negative_flag = 0;
             case(alu_control)
                `ADD: 
                    result <= operand_a + operand_b;
                    
                `SUB: 
                    result <= operand_a - operand_b;
                   
                `ADDS: 
                    begin
                        acc <= operand_a + operand_b;  // Signed arithmetic
                        case(acc[32:31])
                            2'b01:
                                result <= {1'b0, {(32-1){1'b1}}};
                            2'b10: 
                                result <= {1'b1, {(32-1){1'b0}}};
                            default:
                                result <= acc[31:0];
                        endcase

                        overflow_flag <= (acc[32:31] == 2'b01 || acc[32:31] == 2'b10);
                        if (acc[32] == 1'b1)
                            carry_flag = 1;
                        else 
                            carry_flag = 0;
                    end
                `SUBS:
                    result <= operand_a - operand_b;
                    if (result == 0)
                        zero_flag = 1;

                `AND: 
                    result <= operand_a & operand_b;
                  
                `OR: 
                    result <= operand_a | operand_b;
                    
                `XOR: 
                    result <= operand_a ^ operand_b;
                 
                `MVN: 
                    result <= ~operand_a;
                    
                `CMP: 
                    if (operand_a = operand_b)
                        result <= 32'd1;
                    else if (operand_a < operand_b )
                        result = 32'd2;
                    else if (operand_a > operand_b)
                        result = 32'b3;
             endcase
             if (result == 0)
                zero_flag = 1;
        end
endmodule

ALU/ALU_tb.v
`define ADD 4'b0000  // 0b0000 represents addition
`define SUB 4'b0001  // 0b0001 represents subtraction
`define ADDS 4'b0010  // 0b0010 represents add with carry flag
`define SUBS 4'b0011  // 0b0011 represents subtraction with negative flag
`define CMP 4'b0100 // 0b0100 represents comparison
`define AND 4'b0111  // 0b0111 represents bitwise AND
`define OR 4'b1000  // 0b1000 represents bitwise OR
`define XOR 4'b1001  // 0b1001 represents bitwise XOR
`define MVN 4'b1010  // 0b1010 represents bitwise NOT

module ALU_Testbench;

  reg [31:0] operand_a;
  reg [31:0] operand_b;
  reg [3:0] alu_control;
  
  wire [31:0] result;
  wire zero_flag;
  wire carry_flag;
  wire overflow_flag;
  wire negative_flag;

  // Instantiate the ALU module
  ALU uut (
    .operand_a(operand_a),
    .operand_b(operand_b),
    .alu_control(alu_control),
    .result(result),
    .zero_flag(zero_flag),
    .carry_flag(carry_flag),
    .overflow_flag(overflow_flag),
    .negative_flag(negative_flag)
  );

  // Initialize signals
  initial begin
    $dumpfile("ALU_Testbench.vcd");
    $dumpvars(0, ALU_Testbench);

    // Test case 1: Addition
    operand_a = 10;
    operand_b = 20;
    alu_control = `ADD;
    #10;
    
    // Test case 2: Subtraction
    operand_a = 30;
    operand_b = 15;
    alu_control = `SUB;
    #10;

    // Test case 3: Addition with carry flag
    operand_a = 10;
    operand_b = 20;
    alu_control = `ADDS;
    #10;

    // Test case 4: Subtraction with negative flag
    operand_a = -10;
    operand_b = 5;
    alu_control = `SUBS;
    #10;
    
    // Test case 5: Bitwise AND
    operand_a = 0b1100;
    operand_b = 0b1010;
    alu_control = `AND;
    #10;
    
    // Test case 6: Bitwise OR
    operand_a = 0b1100;
    operand_b = 0b1010;
    alu_control = `OR;
    #10;
    
    // Test case 7: Bitwise XOR
    operand_a = 0b1100;
    operand_b = 0b1010;
    alu_control = `XOR;
    #10;
    
    // Test case 8: Bitwise NOT
    operand_a = 0b1100;
    alu_control = `MVN;
    #10;
    
    // Test case 9: Comparison
    operand_a = 10;
    operand_b = 20;
    alu_control = `CMP;
    #10;

    $finish;
  end
endmodule

ALU_testing/ALU_testing.sim/sim_1/behav/xsim/ALU_Testbench.vcd
$date
   Thu Nov  2 11:42:43 2023
$end

$version
  2023.2
  $dumpfile ("ALU_Testbench.vcd") 
$end

$timescale
  1ps
$end

$scope module ALU_Testbench $end
$var reg 32 ! operand_a [31:0] $end
$var reg 32 " operand_b [31:0] $end
$var reg 4 # alu_control [3:0] $end
$var wire 32 $ result [31:0] $end
$var wire 1 % zero_flag $end
$var wire 1 & carry_flag $end
$var wire 1 ' overflow_flag $end
$var wire 1 ( negative_flag $end
$scope module uut $end
$var wire 32 ) operand_a [31:0] $end
$var wire 32 * operand_b [31:0] $end
$var wire 4 + alu_control [3:0] $end
$var reg 32 , result [31:0] $end
$var reg 1 - zero_flag $end
$var reg 1 . carry_flag $end
$var reg 1 / overflow_flag $end
$var reg 1 0 negative_flag $end
$var reg 33 1 acc [32:0] $end
$upscope $end
$upscope $end
$enddefinitions $end

#0
$dumpvars
b1010 !
b10100 "
b0 #
b11110 $
0%
0&
0'
0(
b1010 )
b10100 *
b0 +
b11110 ,
0-
0.
0/
00
bx 1
$end

#10000
b11110 !
b1111 "
b1 #
b1111 $
b11110 )
b1111 *
b1 +
b1111 ,

#20000
b1010 !
b10100 "
b10 #
b11110 $
b1010 )
b10100 *
b10 +
b11110 ,
0/
b11110 1

#30000
b11111111111111111111111111110110 !
b101 "
b11 #
b11111111111111111111111111110001 $
1(
b11111111111111111111111111110110 )
b101 *
b11 +
b11111111111111111111111111110001 ,
10

#40000
b1100 !
b1010 "
b111 #
b1000 $
0(
b1100 )
b1010 *
b111 +
b1000 ,
00

#50000
b1000 #
b1110 $
b1000 +
b1110 ,

#60000
b1001 #
b110 $
b1001 +
b110 ,

#70000
b1010 #
b11111111111111111111111111110011 $
b1010 +
b11111111111111111111111111110011 ,

#80000
b1010 !
b10100 "
b100 #
b10 $
b1010 )
b10100 *
b100 +
b10 ,
