ALU/ALU.v
////////////stuff left : CPSR updation variable and result writeback variable 
`define AND 4'd0
`define EOR 4'd1 //same as XOR
`define SUB 4'd2
`define RSB 4'd3 //Reverse subtraction
`define ADD 4'd4
`define ADC 4'd5
`define SBC 4'd6
`define RSC 4'd7
`define TST 4'd8 
`define TEQ 4'd9
`define CMP 4'd10
`define CMN 4'd11
`define ORR 4'd12
`define MOV 4'd13
`define BIC 4'd14
`define MVN 4'd15
module ALU(
    input signed [31:0] operand_a, operand_b,// the signed part needs to be checked
    input [3:0] alu_control,
    output reg [31:0] result,
    output reg [3:0] nzcv,
    input reset,
    output reg result_writeback,
    output reg nzcv_writeback
);

reg [32:0] acc,temp;
reg carry_flag,overflow_flag,negative_flag,zero_flag;
always @(*)
    if(reset)
        begin
            zero_flag = 0;
            carry_flag = 0;
            overflow_flag = 0;
            negative_flag = 0;    
        end
    else begin

         case(alu_control)
            `ADD:begin
                    acc <= operand_a + operand_b;  // Signed arithmetic
                    case(acc[32:31])
                        2'b01:
                            result = {1'b0, {(32-1){1'b1}}};
                        2'b10: 
                            result = {1'b1, {(32-1){1'b0}}};
                        default:
                            result = acc[31:0];
                    endcase
                    overflow_flag = (acc[32:31] == 2'b01 || acc[32:31] == 2'b10);
                    carry_flag = (acc[32] == 1'b1);
                 end
            `ADC:begin
                    acc = operand_a + operand_b+carry_flag;  // Signed arithmetic
                    case(acc[32:31])
                        2'b01:
                            result = {1'b0, {(32-1){1'b1}}};
                        2'b10: 
                            result = {1'b1, {(32-1){1'b0}}};
                        default:
                            result = acc[31:0];
                    endcase
                    overflow_flag = (acc[32:31] == 2'b01 || acc[32:31] == 2'b10);
                    carry_flag = (acc[32] == 1'b1);
                end
                
            `SUB:begin
                    result = operand_a - operand_b;
                    overflow_flag = (operand_a ^ operand_b) & (operand_a ^ result);
                    negative_flag = (result[31] == 1'b1) ? 1'b1 : 1'b0;
                 end
            `SBC:begin
                    {carry_flag, result} = operand_a - operand_b - ~carry_flag;
                    zero_flag = (result == 32'd0) ;
                 end
            `RSC:begin
                    {carry_flag, result} = operand_b - operand_a - ~carry_flag;
                    zero_flag = (result == 32'd0) ;
                 end
            `AND: begin
                    result = operand_a & operand_b;
                    zero_flag = (result == 32'd0) ;
                end
            `BIC: begin
                    result = operand_a & (~operand_b);
                    zero_flag = (result == 32'd0) ;
                end
            `TST: 
                {negative_flag, zero_flag} = {operand_a[31] & operand_b[31], (operand_a & operand_b) == 0};
            `TEQ:
                {negative_flag, zero_flag} = {operand_a[31] ^ operand_b[31], (operand_a ^ operand_b) == 0};
              
            `ORR:begin 
                    result = operand_a | operand_b;
                    zero_flag = (result == 32'd0) ;
                end
            `EOR:begin
                    result = operand_a ^ operand_b;
                    zero_flag = (result == 32'd0) ;
                end
            `MVN:begin
                    result = ~operand_a;
                    zero_flag = (result == 32'd0) ;
                end
            `RSB:begin
                    result = operand_b - operand_a;  
                    zero_flag = (result == 32'd0) ;
                end
            `CMP:{negative_flag, zero_flag, carry_flag, overflow_flag} = {operand_a[31], (operand_a - operand_b == 0), (operand_a >= operand_b), (operand_a[31] & ~operand_b[31] & ((operand_a - operand_b) >> 31))};

            `CMN:{negative_flag, zero_flag, carry_flag, overflow_flag} = {operand_a[31], (operand_a + operand_b == 0), (operand_a + operand_b < operand_a), (operand_a[31] & operand_b[31] & ~((operand_a + operand_b) >> 31))};
         endcase

        nzcv  = {negative_flag,zero_flag,carry_flag,overflow_flag};
    end
endmodule

ALU/ALU_tb.v
// `include "ALU.v"
// Macros for ALU control signals
`define AND 4'd0
`define EOR 4'd1 // same as XOR
`define SUB 4'd2
`define RSB 4'd3 // Reverse subtraction
`define ADD 4'd4
`define ADC 4'd5
`define SBC 4'd6
`define RSC 4'd7
`define TST 4'd8
`define TEQ 4'd9
`define CMP 4'd10
`define CMN 4'd11
`define ORR 4'd12
`define MOV 4'd13
`define BIC 4'd14
`define MVN 4'd15
module ALU_tb;


  // Signals
  reg signed [31:0] operand_a, operand_b;
  reg [3:0] alu_control;
  reg reset;
  wire [31:0] result;
  wire [3:0] nzcv;
  wire result_writeback;

  // Instantiate the ALU module
  ALU uut(
    .operand_a(operand_a),
    .operand_b(operand_b),
    .alu_control(alu_control),
    .result(result),
    .nzcv(nzcv),
    .reset(reset),
    .result_writeback(result_writeback)
  );

  // Initial block for stimulus
  initial begin
    $dumpfile("ALU.vcd");
    $dumpvars(0, ALU_tb);
    reset = 1;
    operand_a = 32'd10;
    operand_b = 32'd20;
    #10;
    // Test case 1: ADD
    reset = 0;
    operand_a = 32'd10;
    operand_b = 32'd20;
    alu_control = `ADD; // ADD
    

    #10;

    // Test case 2: SUB
    operand_a = 32'd30;
    operand_b = 32'd10;
    alu_control = `SUB; // SUB
    reset = 0;

    #10;

    // Test case 3: AND
    operand_a = 32'd8;
    operand_b = 32'd5;
    alu_control = `AND; // AND
    reset = 0;

    #10;

    // Test case 4: EOR
    operand_a = 32'd15;
    operand_b = 32'd7;
    alu_control = `EOR; // EOR
    reset = 0;

    #10;

    // Test case 5: RSB
    operand_a = 32'd10;
    operand_b = 32'd20;
    alu_control = `RSB; // RSB
    reset = 0;

    #10;

    // Test case 6: ADC
    operand_a = 32'd2147483647; // Maximum positive signed 32-bit number
    operand_b = 32'd1;
    alu_control = `ADC; // ADC
    reset = 0;

    #10;

    // Test case 7: SBC
    operand_a = 32'd2147483647; // Maximum positive signed 32-bit number
    operand_b = 32'd5;
    alu_control = `SBC; // SBC
    reset = 0;

    #10;

    // Test case 8: RSC
    operand_a = 32'd10;
    operand_b = 32'd20;
    alu_control = `RSC; // RSC
    reset = 0;

    #10;

    // Test case 9: TST
    operand_a = 32'd0;
    operand_b = 32'd0;
    alu_control = `TST; // TST
    reset = 0;

    #10;

    // Test case 10: TEQ
    operand_a = 32'd255;
    operand_b = 32'd255;
    alu_control = `TEQ; // TEQ
    reset = 0;

    #10;

    // Test case 11: CMP
    operand_a = 32'd5;
    operand_b = 32'd3;
    alu_control = `CMP; // CMP
    reset = 0;

    #10;

    // Test case 12: CMN
    operand_a = 32'd2147483647; // Maximum positive signed 32-bit number
    operand_b = 32'd1;
    alu_control = `CMN; // CMN
    reset = 0;

    #10;

    // Test case 13: ORR
    operand_a = 32'd10;
    operand_b = 32'd20;
    alu_control = `ORR; // ORR
    reset = 0;

    #10;

    // Test case 14: MOV
    operand_a = 32'd42;
    operand_b = 32'd0;
    alu_control = `MOV; // MOV
    reset = 0;

    #10;

    // Test case 15: BIC
    operand_a = 32'd255;
    operand_b = 32'd85;
    alu_control = `BIC; // BIC
    reset = 0;

    #10;

    // Test case 16: MVN
    operand_a = 32'd255;
    operand_b = 32'd0;
    alu_control = `MVN; // MVN
    reset = 0;

    #10;

    // Add more test cases as needed

    // End simulation
    $finish;
  end

endmodule

ALU/ALU.vcd
$date
	Tue Dec 12 18:16:14 2023
$end
$version
	Icarus Verilog
$end
$timescale
	1s
$end
$scope module ALU_tb $end
$var wire 1 ! result_writeback $end
$var wire 32 " result [31:0] $end
$var wire 4 # nzcv [3:0] $end
$var reg 4 $ alu_control [3:0] $end
$var reg 32 % operand_a [31:0] $end
$var reg 32 & operand_b [31:0] $end
$var reg 1 ' reset $end
$scope module uut $end
$var wire 4 ( alu_control [3:0] $end
$var wire 32 ) operand_a [31:0] $end
$var wire 32 * operand_b [31:0] $end
$var wire 1 ' reset $end
$var reg 33 + acc [32:0] $end
$var reg 1 , carry_flag $end
$var reg 1 - negative_flag $end
$var reg 4 . nzcv [3:0] $end
$var reg 1 / overflow_flag $end
$var reg 32 0 result [31:0] $end
$var reg 1 ! result_writeback $end
$var reg 1 1 zero_flag $end
$upscope $end
$upscope $end
$enddefinitions $end
$comment Show the parameter values. $end
$dumpall
$end
#0
$dumpvars
01
b0 0
0/
b0 .
0-
0,
bx +
b10100 *
b1010 )
bx (
1'
b10100 &
b1010 %
bx $
b0 #
b0 "
0!
$end
#10
b11110 +
b0 #
b0 .
1!
0,
0/
b11110 "
b11110 0
b100 $
b100 (
0'
#20
b10100 "
b10100 0
b10 $
b10 (
b1010 &
b1010 *
b11110 %
b11110 )
#30
b100 #
b100 .
11
b0 "
b0 0
b0 $
b0 (
b101 &
b101 *
b1000 %
b1000 )
#40
b0 #
b0 .
01
b1000 "
b1000 0
b1 $
b1 (
b111 &
b111 *
b1111 %
b1111 )
#50
b1010 "
b1010 0
b11 $
b11 (
b10100 &
b10100 *
b1010 %
b1010 )
#60
b1 #
b1 .
1/
b1111111111111111111111111111111 "
b1111111111111111111111111111111 0
b10000000000000000000000000000000 +
b101 $
b101 (
b1 &
b1 *
b1111111111111111111111111111111 %
b1111111111111111111111111111111 )
#70
b1111111111111111111111111111011 "
b1111111111111111111111111111011 0
b110 $
b110 (
b101 &
b101 *
#80
b1011 "
b1011 0
b111 $
b111 (
b10100 &
b10100 *
b1010 %
b1010 )
#90
b101 #
b101 .
0!
11
b1000 $
b1000 (
b0 &
b0 *
b0 %
b0 )
#100
b1001 $
b1001 (
b11111111 &
b11111111 *
b11111111 %
b11111111 )
#110
b0 #
b0 .
1!
01
0/
b1010 $
b1010 (
b11 &
b11 *
b101 %
b101 )
#120
b1011 $
b1011 (
b1 &
b1 *
b1111111111111111111111111111111 %
b1111111111111111111111111111111 )
#130
b11110 "
b11110 0
b1100 $
b1100 (
b10100 &
b10100 *
b1010 %
b1010 )
#140
b1101 $
b1101 (
b0 &
b0 *
b101010 %
b101010 )
#150
b10101010 "
b10101010 0
b1110 $
b1110 (
b1010101 &
b1010101 *
b11111111 %
b11111111 )
#160
b11111111111111111111111100000000 "
b11111111111111111111111100000000 0
b1111 $
b1111 (
b0 &
b0 *
