ALU/ALU.v
////////////stuff left : CPSR updation variable and result writeback variable 
`define AND 4'd0
`define EOR 4'd1 //same as XOR
`define SUB 4'd2
`define RSB 4'd3 //Reverse subtraction
`define ADD 4'd4
`define ADC 4'd5
`define SBC 4'd6
`define RSC 4'd7
`define TST 4'd8 
`define TEQ 4'd9
`define CMP 4'd10
`define CMN 4'd11
`define ORR 4'd12
`define MOV 4'd13
`define BIC 4'd14
`define MVN 4'd15
module ALU(
    input signed [31:0] operand_a, operand_b,// the signed part needs to be checked
    input [3:0] alu_control,
    output reg [31:0] result,
    output reg [3:0] nzcv,
    input reset,
    output reg result_writeback,
    output reg nzcv_writeback
);

reg [32:0] acc,temp;
reg carry_flag,overflow_flag,negative_flag,zero_flag;
always @(*)
    if(reset)
        begin
            zero_flag = 0;
            carry_flag = 0;
            overflow_flag = 0;
            negative_flag = 0;    
        end
    else begin

         case(alu_control)
            `ADD:begin
                    acc <= operand_a + operand_b;  // Signed arithmetic
                    case(acc[32:31])
                        2'b01:
                            result = {1'b0, {(32-1){1'b1}}};
                        2'b10: 
                            result = {1'b1, {(32-1){1'b0}}};
                        default:
                            result = acc[31:0];
                    endcase
                    overflow_flag = (acc[32:31] == 2'b01 || acc[32:31] == 2'b10);
                    carry_flag = (acc[32] == 1'b1);
                 end
            `ADC:begin
                    acc = operand_a + operand_b+carry_flag;  // Signed arithmetic
                    case(acc[32:31])
                        2'b01:
                            result = {1'b0, {(32-1){1'b1}}};
                        2'b10: 
                            result = {1'b1, {(32-1){1'b0}}};
                        default:
                            result = acc[31:0];
                    endcase
                    overflow_flag = (acc[32:31] == 2'b01 || acc[32:31] == 2'b10);
                    carry_flag = (acc[32] == 1'b1);
                end
                
            `SUB:begin
                    result = operand_a - operand_b;
                    overflow_flag = (operand_a ^ operand_b) & (operand_a ^ result);
                    negative_flag = (result[31] == 1'b1) ? 1'b1 : 1'b0;
                 end
            `SBC:begin
                    {carry_flag, result} = operand_a - operand_b - ~carry_flag;
                    zero_flag = (result == 32'd0) ;
                 end
            `RSC:begin
                    {carry_flag, result} = operand_b - operand_a - ~carry_flag;
                    zero_flag = (result == 32'd0) ;
                 end
            `AND: begin
                    result = operand_a & operand_b;
                    zero_flag = (result == 32'd0) ;
                end
            `BIC: begin
                    result = operand_a & (~operand_b);
                    zero_flag = (result == 32'd0) ;
                end
            `TST: 
                {negative_flag, zero_flag} = {operand_a[31] & operand_b[31], (operand_a & operand_b) == 0};
            `TEQ:
                {negative_flag, zero_flag} = {operand_a[31] ^ operand_b[31], (operand_a ^ operand_b) == 0};
              
            `ORR:begin 
                    result = operand_a | operand_b;
                    zero_flag = (result == 32'd0) ;
                end
            `EOR:begin
                    result = operand_a ^ operand_b;
                    zero_flag = (result == 32'd0) ;
                end
            `MVN:begin
                    result = ~operand_a;
                    zero_flag = (result == 32'd0) ;
                end
            `RSB:begin
                    result = operand_b - operand_a;  
                    zero_flag = (result == 32'd0) ;
                end
            `CMP:{negative_flag, zero_flag, carry_flag, overflow_flag} = {operand_a[31], (operand_a - operand_b == 0), (operand_a >= operand_b), (operand_a[31] & ~operand_b[31] & ((operand_a - operand_b) >> 31))};

            `CMN:{negative_flag, zero_flag, carry_flag, overflow_flag} = {operand_a[31], (operand_a + operand_b == 0), (operand_a + operand_b < operand_a), (operand_a[31] & operand_b[31] & ~((operand_a + operand_b) >> 31))};
         endcase

        nzcv  = {negative_flag,zero_flag,carry_flag,overflow_flag};
    end
endmodule

ALU/ALU_tb.v
`include "ALU.v"
`define AND 4'd0
`define EOR 4'd1 //same as XOR
`define SUB 4'd2
`define RSB 4'd3 //Reverse subtraction
`define ADD 4'd4
`define ADC 4'd5
`define SBC 4'd6
`define RSC 4'd7
`define TST 4'd8 
`define TEQ 4'd9
`define CMP 4'd10
`define CMN 4'd11
`define ORR 4'd12
`define MOV 4'd13
`define BIC 4'd14
`define MVN 4'd15
module ALU_tb;
  reg signed [31:0] operand_a, operand_b;
  reg [3:0] alu_control;
  reg reset;
  wire [31:0] result;
  wire [3:0] nzcv;
  wire result_writeback, nzcv_writeback;

  ALU myALU (
    .operand_a(operand_a),
    .operand_b(operand_b),
    .alu_control(alu_control),
    .result(result),
    .nzcv(nzcv),
    .reset(reset),
    .result_writeback(result_writeback),
    .nzcv_writeback(nzcv_writeback)
  );

  initial begin
    // Test Case 0: AND
    operand_a = 8'b11001100;
    operand_b = 8'b10101010;
    alu_control = `AND;
    reset = 0;
    #10;

    // Test Case 1: EOR
    operand_a = 8'b11001100;
    operand_b = 8'b10101010;
    alu_control = `EOR;
    reset = 0;
    #10;
    
    // Test Case 2: SUB
    operand_a = 20;
    operand_b = 15;
    alu_control = `SUB;
    reset = 0;
    #10;
    
    // Test Case 3: RSB
    operand_a = 5;
    operand_b = 10;
    alu_control = `RSB;
    reset = 0;
    #10;
    
    // Test Case 4: ADD
    operand_a = 5;
    operand_b = 3;
    alu_control = `ADD;
    reset = 0;
    #10;

    // Test Case 5: ADC
    operand_a = 10;
    operand_b = 15;
    alu_control = `ADC;
    reset = 0;
    #10;

    // Test Case 6: SBC
    operand_a = 15;
    operand_b = 8;
    alu_control = `SBC;
    reset = 0;
    #10;

   // Test Case 7: RSC
    operand_a = 20;
    operand_b = 15;
    alu_control = `RSC;
    reset = 0;
    #10;

    // Test Case 8: TST
    operand_a = 8'b11001100;
    operand_b = 8'b10101010;
    alu_control = `TST;
    reset = 0;
    #10;

    // Test Case 9: TEQ
    operand_a = 8'b11001100;
    operand_b = 8'b10101010;
    alu_control = `TEQ;
    reset = 0;
    #10;

    // Test Case 10: CMP
    operand_a = 10;
    operand_b = 5;
    alu_control = `CMP;
    reset = 0;
    #10;

    // Test Case 11: CMN
    operand_a = 10;
    operand_b = 5;
    alu_control = `CMN;
    reset = 0;
    #10;

    // Test Case 12: ORR
    operand_a = 8'b11001100;
    operand_b = 8'b10101010;
    alu_control = `ORR;
    reset = 0;
    #10;

    // Test Case 13: MOV
    operand_a = 8'b11001100;
    operand_b = 8'b10101010;
    alu_control = `MOV;
    reset = 0;
    #10;

    // Test Case 14: BIC
    operand_a = 8'b11001100;
    operand_b = 8'b10101010;
    alu_control = `BIC;
    reset = 0;
    #10;

    // Test Case 15: MVN
    operand_a = 8'b11001100;
    operand_b = 8'b10101010;
    alu_control = `MVN;
    reset = 0;
    #10;

    $finish;
  end

  initial begin 
    $dumpfile("ALU.vcd");
    $dumpvars;
  end 

endmodule

ALU/ALU.vcd
$date
	Sun Dec 10 18:36:42 2023
$end
$version
	Icarus Verilog
$end
$timescale
	1s
$end
$scope module ALU_tb $end
$var wire 1 ! result_writeback $end
$var wire 32 " result [31:0] $end
$var wire 1 # nzcv_writeback $end
$var wire 4 $ nzcv [3:0] $end
$var reg 4 % alu_control [3:0] $end
$var reg 32 & operand_a [31:0] $end
$var reg 32 ' operand_b [31:0] $end
$var reg 1 ( reset $end
$scope module myALU $end
$var wire 4 ) alu_control [3:0] $end
$var wire 32 * operand_a [31:0] $end
$var wire 32 + operand_b [31:0] $end
$var wire 1 ( reset $end
$var reg 33 , acc [32:0] $end
$var reg 1 - carry_flag $end
$var reg 1 . negative_flag $end
$var reg 4 / nzcv [3:0] $end
$var reg 1 # nzcv_writeback $end
$var reg 1 0 overflow_flag $end
$var reg 32 1 result [31:0] $end
$var reg 1 ! result_writeback $end
$var reg 1 2 zero_flag $end
$upscope $end
$upscope $end
$enddefinitions $end
$comment Show the parameter values. $end
$dumpall
$end
#0
$dumpvars
02
b10001000 1
x0
bx0xx /
x.
x-
bx ,
b10101010 +
b11001100 *
b0 )
0(
b10101010 '
b11001100 &
b0 %
bx0xx $
x#
b10001000 "
x!
$end
#10
b1100110 "
b1100110 1
b1 %
b1 )
#20
b0x1 $
b0x1 /
0.
10
b101 "
b101 1
b10 %
b10 )
b1111 '
b1111 +
b10100 &
b10100 *
#30
b11 %
b11 )
b1010 '
b1010 +
b101 &
b101 *
#40
0-
b1000 ,
b0 $
b0 /
00
b1000 "
b1000 1
b100 %
b100 )
b11 '
b11 +
#50
b11001 "
b11001 1
b11001 ,
b101 %
b101 )
b1111 '
b1111 +
b1010 &
b1010 *
#60
b1000 "
b1000 1
b110 %
b110 )
b1000 '
b1000 +
b1111 &
b1111 *
#70
b10 $
b10 /
1-
b11111111111111111111111111111100 "
b11111111111111111111111111111100 1
b111 %
b111 )
b1111 '
b1111 +
b10100 &
b10100 *
#80
b1000 %
b1000 )
b10101010 '
b10101010 +
b11001100 &
b11001100 *
#90
b1001 %
b1001 )
#100
b0 $
b0 /
0-
b1010 %
b1010 )
b101 '
b101 +
b1010 &
b1010 *
#110
b1011 %
b1011 )
#120
b11101110 "
b11101110 1
b1100 %
b1100 )
b10101010 '
b10101010 +
b11001100 &
b11001100 *
#130
b1101 %
b1101 )
#140
b1000100 "
b1000100 1
b1110 %
b1110 )
#150
b11111111111111111111111100110011 "
b11111111111111111111111100110011 1
b1111 %
b1111 )
